buildlib/__init__.py
buildlib/buildmisc/__init__.py
buildlib/buildmisc/cmd.py
buildlib/buildmisc/lib.py
buildlib/buildmisc/prompt.py
buildlib/git/__init__.py
buildlib/git/cmd.py
buildlib/git/lib.py
buildlib/git/prompt.py
buildlib/git/seq.py
buildlib/npm/__init__.py
buildlib/npm/cmd.py
buildlib/npm/lib.py
buildlib/npm/prompt.py
buildlib/pip/__init__.py
buildlib/pip/cmd.py
buildlib/pip/lib.py
buildlib/pipenv/__init__.py
buildlib/pipenv/cmd.py
buildlib/pipenv/lib.py
buildlib/project/__init__.py
buildlib/project/cmd.py
buildlib/project/lib.py
buildlib/project/prompt.py
buildlib/semver/__init__.py
buildlib/semver/lib.py
buildlib/semver/prompt.py
buildlib/utils/__init__.py
buildlib/wheel/__init__.py
buildlib/wheel/cmd.py
buildlib/wheel/lib.py
buildlib/wheel/prompt.py
buildlib/yaml_/__init__.py
buildlib-3.0.2.dist-info/METADATA
buildlib-3.0.2.dist-info/WHEEL
buildlib-3.0.2.dist-info/top_level.txt
buildlib-3.0.2.dist-info/RECORD
